phenix_apps/__init__.py
phenix_apps/apps/__init__.py
phenix_apps/apps/protonuke/__init__.py
phenix_apps/apps/protonuke/protonuke.py
phenix_apps/apps/wireguard/__init__.py
phenix_apps/apps/wireguard/wireguard.py
phenix_apps/common/__init__.py
phenix_apps/common/error.py
phenix_apps/common/logger.py
phenix_apps/common/settings.py
phenix_apps/common/utils.py
phenix_apps/schedulers/__init__.py
phenix_apps/schedulers/single_node/__init__.py
phenix_apps/schedulers/single_node/single_node.py
phenix_apps-0.2.0.dist-info/LICENSE
phenix_apps-0.2.0.dist-info/METADATA
phenix_apps-0.2.0.dist-info/WHEEL
phenix_apps-0.2.0.dist-info/entry_points.txt
phenix_apps-0.2.0.dist-info/top_level.txt
phenix_apps-0.2.0.dist-info/RECORD
