Metadata-Version: 2.1
Name: phenix-apps
Version: 0.2.0
Summary: User apps and schedulers for phenix orchestration
Home-page: https://github.com/activeshadow/phenix-apps
Author: Bryan Richardson, Active Shadow LLC
License: UNKNOWN
Platform: Linux
Classifier: Development Status :: 4 - Beta
Classifier: License :: OSI Approved :: GNU General Public License v3 (GPLv3)
Classifier: Operating System :: POSIX :: Linux
Classifier: Programming Language :: Python :: 3.7
Requires-Python: >=3.7
Requires-Dist: Mako (~=1.1.3)
Requires-Dist: python-box (~=5.1.1)
